<?xml version="1.0" encoding="UTF-8"?>
<sv:node sv:name="andreas" xmlns:sv="http://www.jcp.org/jcr/sv/1.0" xmlns:xsi="http://www.w3.org/2001/XMLSchema-instance">
  <sv:property sv:name="jcr:primaryType" sv:type="Name">
    <sv:value>mgnl:user</sv:value>
  </sv:property>
  <sv:property sv:name="jcr:mixinTypes" sv:type="Name" sv:multiple="true">
    <sv:value>mix:lockable</sv:value>
  </sv:property>
  <sv:property sv:name="jcr:uuid" sv:type="String">
    <sv:value>0fb250c1-9b66-4efc-8822-b0d3243de322</sv:value>
  </sv:property>
  <sv:property sv:name="email" sv:type="String">
    <sv:value>andreas.weder@magnolia-cms.com</sv:value>
  </sv:property>
  <sv:property sv:name="enabled" sv:type="String">
    <sv:value>true</sv:value>
  </sv:property>
  <sv:property sv:name="jcr:createdBy" sv:type="String">
    <sv:value>admin</sv:value>
  </sv:property>
  <sv:property sv:name="language" sv:type="String">
    <sv:value>en</sv:value>
  </sv:property>
  <sv:property sv:name="lastaccess" sv:type="Date">
    <sv:value>2014-06-24T22:22:59.634+02:00</sv:value>
  </sv:property>
  <sv:property sv:name="mgnl:activationStatus" sv:type="Boolean">
    <sv:value>true</sv:value>
  </sv:property>
  <sv:property sv:name="mgnl:created" sv:type="Date">
    <sv:value>2014-06-24T11:20:46.992+02:00</sv:value>
  </sv:property>
  <sv:property sv:name="mgnl:createdBy" sv:type="String">
    <sv:value>superuser</sv:value>
  </sv:property>
  <sv:property sv:name="mgnl:lastActivated" sv:type="Date">
    <sv:value>2014-06-24T22:03:18.246+02:00</sv:value>
  </sv:property>
  <sv:property sv:name="mgnl:lastActivatedBy" sv:type="String">
    <sv:value>superuser</sv:value>
  </sv:property>
  <sv:property sv:name="mgnl:lastModified" sv:type="Date">
    <sv:value>2014-06-24T22:22:59.634+02:00</sv:value>
  </sv:property>
  <sv:property sv:name="mgnl:lastModifiedBy" sv:type="String">
    <sv:value>superuser</sv:value>
  </sv:property>
  <sv:property sv:name="name" sv:type="String">
    <sv:value>andreas</sv:value>
  </sv:property>
  <sv:property sv:name="pswd" sv:type="String">
    <sv:value>$2a$12$BLM.1L/sYGIb.jqx1y27juJPJyPEsslf4YMihdFc1oy3.xKxFWu86</sv:value>
  </sv:property>
  <sv:property sv:name="title" sv:type="String">
    <sv:value>Andreas Weder</sv:value>
  </sv:property>
  <sv:node sv:name="acl_users">
    <sv:property sv:name="jcr:primaryType" sv:type="Name">
      <sv:value>mgnl:contentNode</sv:value>
    </sv:property>
    <sv:property sv:name="jcr:uuid" sv:type="String">
      <sv:value>a1e2b981-69b6-4972-be20-dfb823d85e14</sv:value>
    </sv:property>
    <sv:property sv:name="jcr:createdBy" sv:type="String">
      <sv:value>admin</sv:value>
    </sv:property>
    <sv:property sv:name="mgnl:activationStatus" sv:type="Boolean">
      <sv:value>true</sv:value>
    </sv:property>
    <sv:property sv:name="mgnl:created" sv:type="Date">
      <sv:value>2014-06-24T11:20:47.326+02:00</sv:value>
    </sv:property>
    <sv:property sv:name="mgnl:createdBy" sv:type="String">
      <sv:value>superuser</sv:value>
    </sv:property>
    <sv:property sv:name="mgnl:lastActivated" sv:type="Date">
      <sv:value>2014-06-24T22:03:18.247+02:00</sv:value>
    </sv:property>
    <sv:property sv:name="mgnl:lastActivatedBy" sv:type="String">
      <sv:value>superuser</sv:value>
    </sv:property>
    <sv:property sv:name="mgnl:lastModified" sv:type="Date">
      <sv:value>2014-06-24T11:20:47.326+02:00</sv:value>
    </sv:property>
    <sv:property sv:name="mgnl:lastModifiedBy" sv:type="String">
      <sv:value>superuser</sv:value>
    </sv:property>
    <sv:node sv:name="0">
      <sv:property sv:name="jcr:primaryType" sv:type="Name">
        <sv:value>mgnl:contentNode</sv:value>
      </sv:property>
      <sv:property sv:name="jcr:uuid" sv:type="String">
        <sv:value>6f1c7b96-2614-44fa-8fdd-f302b9ce78e3</sv:value>
      </sv:property>
      <sv:property sv:name="jcr:createdBy" sv:type="String">
        <sv:value>admin</sv:value>
      </sv:property>
      <sv:property sv:name="mgnl:activationStatus" sv:type="Boolean">
        <sv:value>true</sv:value>
      </sv:property>
      <sv:property sv:name="mgnl:created" sv:type="Date">
        <sv:value>2014-06-24T11:20:47.327+02:00</sv:value>
      </sv:property>
      <sv:property sv:name="mgnl:createdBy" sv:type="String">
        <sv:value>superuser</sv:value>
      </sv:property>
      <sv:property sv:name="mgnl:lastActivated" sv:type="Date">
        <sv:value>2014-06-24T22:03:18.247+02:00</sv:value>
      </sv:property>
      <sv:property sv:name="mgnl:lastActivatedBy" sv:type="String">
        <sv:value>superuser</sv:value>
      </sv:property>
      <sv:property sv:name="mgnl:lastModified" sv:type="Date">
        <sv:value>2014-06-24T11:20:47.327+02:00</sv:value>
      </sv:property>
      <sv:property sv:name="mgnl:lastModifiedBy" sv:type="String">
        <sv:value>superuser</sv:value>
      </sv:property>
      <sv:property sv:name="path" sv:type="String">
        <sv:value>/admin/andreas</sv:value>
      </sv:property>
      <sv:property sv:name="permissions" sv:type="Long">
        <sv:value>8</sv:value>
      </sv:property>
    </sv:node>
    <sv:node sv:name="00">
      <sv:property sv:name="jcr:primaryType" sv:type="Name">
        <sv:value>mgnl:contentNode</sv:value>
      </sv:property>
      <sv:property sv:name="jcr:uuid" sv:type="String">
        <sv:value>74dc3c38-25fe-46cd-96de-29b0f526887f</sv:value>
      </sv:property>
      <sv:property sv:name="jcr:createdBy" sv:type="String">
        <sv:value>admin</sv:value>
      </sv:property>
      <sv:property sv:name="mgnl:activationStatus" sv:type="Boolean">
        <sv:value>true</sv:value>
      </sv:property>
      <sv:property sv:name="mgnl:created" sv:type="Date">
        <sv:value>2014-06-24T11:20:47.327+02:00</sv:value>
      </sv:property>
      <sv:property sv:name="mgnl:createdBy" sv:type="String">
        <sv:value>superuser</sv:value>
      </sv:property>
      <sv:property sv:name="mgnl:lastActivated" sv:type="Date">
        <sv:value>2014-06-24T22:03:18.247+02:00</sv:value>
      </sv:property>
      <sv:property sv:name="mgnl:lastActivatedBy" sv:type="String">
        <sv:value>superuser</sv:value>
      </sv:property>
      <sv:property sv:name="mgnl:lastModified" sv:type="Date">
        <sv:value>2014-06-24T11:20:47.327+02:00</sv:value>
      </sv:property>
      <sv:property sv:name="mgnl:lastModifiedBy" sv:type="String">
        <sv:value>superuser</sv:value>
      </sv:property>
      <sv:property sv:name="path" sv:type="String">
        <sv:value>/admin/andreas/email</sv:value>
      </sv:property>
      <sv:property sv:name="permissions" sv:type="Long">
        <sv:value>63</sv:value>
      </sv:property>
    </sv:node>
    <sv:node sv:name="01">
      <sv:property sv:name="jcr:primaryType" sv:type="Name">
        <sv:value>mgnl:contentNode</sv:value>
      </sv:property>
      <sv:property sv:name="jcr:uuid" sv:type="String">
        <sv:value>e6069bb0-08e5-4017-b096-f41131bd9543</sv:value>
      </sv:property>
      <sv:property sv:name="jcr:createdBy" sv:type="String">
        <sv:value>admin</sv:value>
      </sv:property>
      <sv:property sv:name="mgnl:activationStatus" sv:type="Boolean">
        <sv:value>true</sv:value>
      </sv:property>
      <sv:property sv:name="mgnl:created" sv:type="Date">
        <sv:value>2014-06-24T11:20:47.328+02:00</sv:value>
      </sv:property>
      <sv:property sv:name="mgnl:createdBy" sv:type="String">
        <sv:value>superuser</sv:value>
      </sv:property>
      <sv:property sv:name="mgnl:lastActivated" sv:type="Date">
        <sv:value>2014-06-24T22:03:18.247+02:00</sv:value>
      </sv:property>
      <sv:property sv:name="mgnl:lastActivatedBy" sv:type="String">
        <sv:value>superuser</sv:value>
      </sv:property>
      <sv:property sv:name="mgnl:lastModified" sv:type="Date">
        <sv:value>2014-06-24T11:20:47.328+02:00</sv:value>
      </sv:property>
      <sv:property sv:name="mgnl:lastModifiedBy" sv:type="String">
        <sv:value>superuser</sv:value>
      </sv:property>
      <sv:property sv:name="path" sv:type="String">
        <sv:value>/admin/andreas/language</sv:value>
      </sv:property>
      <sv:property sv:name="permissions" sv:type="Long">
        <sv:value>63</sv:value>
      </sv:property>
    </sv:node>
    <sv:node sv:name="02">
      <sv:property sv:name="jcr:primaryType" sv:type="Name">
        <sv:value>mgnl:contentNode</sv:value>
      </sv:property>
      <sv:property sv:name="jcr:uuid" sv:type="String">
        <sv:value>e6434f76-a431-4d3b-969e-8dd588f1a916</sv:value>
      </sv:property>
      <sv:property sv:name="jcr:createdBy" sv:type="String">
        <sv:value>admin</sv:value>
      </sv:property>
      <sv:property sv:name="mgnl:activationStatus" sv:type="Boolean">
        <sv:value>true</sv:value>
      </sv:property>
      <sv:property sv:name="mgnl:created" sv:type="Date">
        <sv:value>2014-06-24T11:20:47.328+02:00</sv:value>
      </sv:property>
      <sv:property sv:name="mgnl:createdBy" sv:type="String">
        <sv:value>superuser</sv:value>
      </sv:property>
      <sv:property sv:name="mgnl:lastActivated" sv:type="Date">
        <sv:value>2014-06-24T22:03:18.247+02:00</sv:value>
      </sv:property>
      <sv:property sv:name="mgnl:lastActivatedBy" sv:type="String">
        <sv:value>superuser</sv:value>
      </sv:property>
      <sv:property sv:name="mgnl:lastModified" sv:type="Date">
        <sv:value>2014-06-24T11:20:47.328+02:00</sv:value>
      </sv:property>
      <sv:property sv:name="mgnl:lastModifiedBy" sv:type="String">
        <sv:value>superuser</sv:value>
      </sv:property>
      <sv:property sv:name="path" sv:type="String">
        <sv:value>/admin/andreas/lastaccess</sv:value>
      </sv:property>
      <sv:property sv:name="permissions" sv:type="Long">
        <sv:value>63</sv:value>
      </sv:property>
    </sv:node>
    <sv:node sv:name="03">
      <sv:property sv:name="jcr:primaryType" sv:type="Name">
        <sv:value>mgnl:contentNode</sv:value>
      </sv:property>
      <sv:property sv:name="jcr:uuid" sv:type="String">
        <sv:value>f04c8426-af78-4928-901b-2dd7190b6902</sv:value>
      </sv:property>
      <sv:property sv:name="jcr:createdBy" sv:type="String">
        <sv:value>admin</sv:value>
      </sv:property>
      <sv:property sv:name="mgnl:activationStatus" sv:type="Boolean">
        <sv:value>true</sv:value>
      </sv:property>
      <sv:property sv:name="mgnl:created" sv:type="Date">
        <sv:value>2014-06-24T11:20:47.329+02:00</sv:value>
      </sv:property>
      <sv:property sv:name="mgnl:createdBy" sv:type="String">
        <sv:value>superuser</sv:value>
      </sv:property>
      <sv:property sv:name="mgnl:lastActivated" sv:type="Date">
        <sv:value>2014-06-24T22:03:18.248+02:00</sv:value>
      </sv:property>
      <sv:property sv:name="mgnl:lastActivatedBy" sv:type="String">
        <sv:value>superuser</sv:value>
      </sv:property>
      <sv:property sv:name="mgnl:lastModified" sv:type="Date">
        <sv:value>2014-06-24T11:20:47.329+02:00</sv:value>
      </sv:property>
      <sv:property sv:name="mgnl:lastModifiedBy" sv:type="String">
        <sv:value>superuser</sv:value>
      </sv:property>
      <sv:property sv:name="path" sv:type="String">
        <sv:value>/admin/andreas/pswd</sv:value>
      </sv:property>
      <sv:property sv:name="permissions" sv:type="Long">
        <sv:value>63</sv:value>
      </sv:property>
    </sv:node>
    <sv:node sv:name="04">
      <sv:property sv:name="jcr:primaryType" sv:type="Name">
        <sv:value>mgnl:contentNode</sv:value>
      </sv:property>
      <sv:property sv:name="jcr:uuid" sv:type="String">
        <sv:value>de3433a0-59d4-4637-b061-2cd0fdbbe9d2</sv:value>
      </sv:property>
      <sv:property sv:name="jcr:createdBy" sv:type="String">
        <sv:value>admin</sv:value>
      </sv:property>
      <sv:property sv:name="mgnl:activationStatus" sv:type="Boolean">
        <sv:value>true</sv:value>
      </sv:property>
      <sv:property sv:name="mgnl:created" sv:type="Date">
        <sv:value>2014-06-24T11:20:47.329+02:00</sv:value>
      </sv:property>
      <sv:property sv:name="mgnl:createdBy" sv:type="String">
        <sv:value>superuser</sv:value>
      </sv:property>
      <sv:property sv:name="mgnl:lastActivated" sv:type="Date">
        <sv:value>2014-06-24T22:03:18.248+02:00</sv:value>
      </sv:property>
      <sv:property sv:name="mgnl:lastActivatedBy" sv:type="String">
        <sv:value>superuser</sv:value>
      </sv:property>
      <sv:property sv:name="mgnl:lastModified" sv:type="Date">
        <sv:value>2014-06-24T11:20:47.329+02:00</sv:value>
      </sv:property>
      <sv:property sv:name="mgnl:lastModifiedBy" sv:type="String">
        <sv:value>superuser</sv:value>
      </sv:property>
      <sv:property sv:name="path" sv:type="String">
        <sv:value>/admin/andreas/title</sv:value>
      </sv:property>
      <sv:property sv:name="permissions" sv:type="Long">
        <sv:value>63</sv:value>
      </sv:property>
    </sv:node>
  </sv:node>
  <sv:node sv:name="groups">
    <sv:property sv:name="jcr:primaryType" sv:type="Name">
      <sv:value>mgnl:contentNode</sv:value>
    </sv:property>
    <sv:property sv:name="jcr:mixinTypes" sv:type="Name" sv:multiple="true">
      <sv:value>mix:lockable</sv:value>
    </sv:property>
    <sv:property sv:name="jcr:uuid" sv:type="String">
      <sv:value>a2d47799-8b02-4e99-a9a5-d821b8310bb0</sv:value>
    </sv:property>
    <sv:property sv:name="0" sv:type="String">
      <sv:value>1e26f515-dbf7-4461-aa40-3bdbb0e8120b</sv:value>
    </sv:property>
    <sv:property sv:name="1" sv:type="String">
      <sv:value>d2729f91-a432-429e-a345-18912815606a</sv:value>
    </sv:property>
    <sv:property sv:name="2" sv:type="String">
      <sv:value>dd17bb54-8cac-484c-a356-9b0582fb39bf</sv:value>
    </sv:property>
    <sv:property sv:name="3" sv:type="String">
      <sv:value>0cd8708b-c13b-4360-bb9c-a276886ec447</sv:value>
    </sv:property>
    <sv:property sv:name="jcr:createdBy" sv:type="String">
      <sv:value>admin</sv:value>
    </sv:property>
    <sv:property sv:name="mgnl:activationStatus" sv:type="Boolean">
      <sv:value>true</sv:value>
    </sv:property>
    <sv:property sv:name="mgnl:lastActivated" sv:type="Date">
      <sv:value>2014-06-24T22:03:18.248+02:00</sv:value>
    </sv:property>
    <sv:property sv:name="mgnl:lastActivatedBy" sv:type="String">
      <sv:value>superuser</sv:value>
    </sv:property>
  </sv:node>
  <sv:node sv:name="roles">
    <sv:property sv:name="jcr:primaryType" sv:type="Name">
      <sv:value>mgnl:contentNode</sv:value>
    </sv:property>
    <sv:property sv:name="jcr:mixinTypes" sv:type="Name" sv:multiple="true">
      <sv:value>mix:lockable</sv:value>
    </sv:property>
    <sv:property sv:name="jcr:uuid" sv:type="String">
      <sv:value>b18def0b-6589-42d0-89a8-5ec5321774f0</sv:value>
    </sv:property>
    <sv:property sv:name="jcr:createdBy" sv:type="String">
      <sv:value>admin</sv:value>
    </sv:property>
    <sv:property sv:name="mgnl:activationStatus" sv:type="Boolean">
      <sv:value>true</sv:value>
    </sv:property>
    <sv:property sv:name="mgnl:lastActivated" sv:type="Date">
      <sv:value>2014-06-24T22:03:18.248+02:00</sv:value>
    </sv:property>
    <sv:property sv:name="mgnl:lastActivatedBy" sv:type="String">
      <sv:value>superuser</sv:value>
    </sv:property>
  </sv:node>
</sv:node>
